clustercron/__init__.py
clustercron/alb.py
clustercron/cache.py
clustercron/config.py
clustercron/elb.py
clustercron/lb.py
clustercron/main.py
clustercron/version.py
clustercron/etc/clustercron.ini
clustercron-1.0.1.dist-info/LICENSE.txt
clustercron-1.0.1.dist-info/METADATA
clustercron-1.0.1.dist-info/WHEEL
clustercron-1.0.1.dist-info/entry_points.txt
clustercron-1.0.1.dist-info/top_level.txt
clustercron-1.0.1.dist-info/RECORD
