Metadata-Version: 2.1
Name: clustercron
Version: 1.0.1
Summary: Cron job wrapper that ensures a script gets run from one node in the cluster.
Home-page: https://github.com/maartenq/clustercron
Author: Maarten
Author-email: ikmaarten@gmail.com
License: ISC
Project-URL: Bug Tracker, https://github.com/maartenq/clustercron/issues
Project-URL: Changelog, https://github.com/maartenq/clustercron/blob/main/HISTORY.rst
Keywords: clustercron
Platform: UNKNOWN
Classifier: Intended Audience :: System Administrators
Classifier: License :: OSI Approved :: ISC License (ISCL)
Classifier: License :: OSI Approved :: MIT License
Classifier: Operating System :: OS Independent
Classifier: Programming Language :: Python :: 3
Classifier: Programming Language :: Python :: 3 :: Only
Classifier: Programming Language :: Python :: 3.6
Classifier: Programming Language :: Python :: 3.7
Classifier: Programming Language :: Python :: 3.8
Classifier: Programming Language :: Python :: 3.9
Classifier: Programming Language :: Python :: 3.10
Classifier: Topic :: System :: Clustering
Requires-Python: >=3.6
License-File: LICENSE.txt
Requires-Dist: boto
Requires-Dist: boto3
Provides-Extra: dev
Requires-Dist: Sphinx ; extra == 'dev'
Requires-Dist: black ; extra == 'dev'
Requires-Dist: build ; extra == 'dev'
Requires-Dist: flake8 ; extra == 'dev'
Requires-Dist: pre-commit ; extra == 'dev'
Requires-Dist: pytest ; extra == 'dev'
Requires-Dist: pytest-cov ; extra == 'dev'
Requires-Dist: responses ; extra == 'dev'
Requires-Dist: sphinx-rtd-theme ; extra == 'dev'
Requires-Dist: tox ; extra == 'dev'
Requires-Dist: twine ; extra == 'dev'
Provides-Extra: docs
Requires-Dist: Sphinx ; extra == 'docs'
Requires-Dist: sphinx-rtd-theme ; extra == 'docs'
Provides-Extra: test
Requires-Dist: pytest ; extra == 'test'
Requires-Dist: pytest-cov ; extra == 'test'
Requires-Dist: responses ; extra == 'test'
